{
"type": "ItemTurret",
  "size": 3,
  "health": 480,
  "reload": 70,
  "range": 300,
  "outlineColor": "#404049",
  "drawer": {
   "type": "DrawTurret",
		"parts": [
		{
			"type": "RegionPart",
			"suffix": "-bottom",
			"under": true,
		  },
		  {
			"type": "RegionPart",
			"suffix": "-la",
			"under": true,
			"progress": "recoil",
			"moveY": -2,
			"moveX": -1,
		  },
		  {
			"type": "RegionPart",
			"suffix": "-ra",
			"under": true,
			"progress": "recoil",
			"moveY": -2,
			"moveX": 1,
		  }

				]    
          },
  "targetAir": false,
  "recoil": 3,
  "rotateSpeed": 3,
  "shootSound": "missile",
  "ammoPerShot": 20,
  "maxAmmo": 100,
  "unitSort": "strongest",
  "coolant": {
    "type": "ConsumeCoolant",
    "amount": 0.4
  },
  "coolantMultiplier": 1.5,
  "consumes": {
    "power": 4
  },
  "ammoTypes": {
    "pyratite": {
      "type": "MissileBulletType",
	  "ammoMultiplier": 1,
	  "homingPower": 0.15,
      "homingRange": 100,
	  "buildingDamageMultiplier": 1.2,
      "lifetime": 100,
      "damage": 15,
	  "speed": 3,
	  "makeFire": true,
	  "incendAmount": 30,
      "fromColor": "ffc859",
      "toColor": "e8b54f",
      "height": 25,
      "width": 10,
      "pierce": false,
      "smokeEffect": "hitBulletBig",
	  "fragBullets": 160,
	  "fragVelocityMin": 0.1,
      "fragVelocityMax": 1,
      "fragCone": 360,
      "fragBullet": {
        "type": "basicBulletType",
		"buildingDamageMultiplier": 0.5,
		"collidesAir": false,	
        "height": 12,
		"speed":1
        "width": 8,
        "lifetime": 100,
        "damage": 5,
        "shrinkY": 1,
		"smokeEffect": "hitBulletBig",
        "despawnEffect": "none",
        "frontColor": "f0ac24",
        "backColor": "e8b54f",
        "pierce": true,
        "pierceBuilding": true,
		"makeFire": true,
		"incendAmount": 30,
		"laserAbsorb": true,
		"pierseCap": 3
	  }
      },
	  "blast-compound": {
      "type": "MissileBulletType",
	  "ammoMultiplier": 1,
	  "homingPower": 0.15,
      "homingRange": 100,
	  "buildingDamageMultiplier": 1.2,
      "lifetime": 100,
      "damage": 30,
	  "speed": 3,
	  "makeFire": true,
	  "incendAmount": 30,
      "fromColor": "ffc859",
      "toColor": "e8b54f",
      "height": 25,
      "width": 10,
      "pierce": false,
      "smokeEffect": "hitBulletBig",
	  "fragBullets": 160,
	  "fragVelocityMin": 0.1,
      "fragVelocityMax": 1,
      "fragCone": 360,
      "fragBullet": {
        "type": "basicBulletType",
		"buildingDamageMultiplier": 0.5,
		"collidesAir": false,
		"smokeEffect": "hitBulletBig",
        "height": 12,
		"speed":1
        "width": 8,
        "lifetime": 100,
        "damage": 10,
        "shrinkY": 1,
        "despawnEffect": "none",
        "frontColor": "f0ac24",
        "backColor": "e8b54f",
        "pierce": true,
        "pierceBuilding": true,
		"makeFire": true,
		"incendAmount": 30,
		"laserAbsorb": true,
		"pierseCap": 5
      }
    }
  },
 "cooldown": 0.009,
 "requirements": [
    {"item": "titanium", "amount": 90},
	{"item": "thorium", "amount": 85},
	{"item": "silicon", "amount": 80},
	{"item": "plastanium", "amount": 70},
    {"item": "graphite", "amount": 60}
  ],
  "category": "turret",
  "research": {
	  "parent":"swarmer"}
}
