{
	"type": "mech",
	"immunities": ["futurehorizons-dissolving"],
	"speed": 0.65,
	"outlineColor": "565666ff",
	"flying": false,
	"health": 11200,
	"armor": 16,
	"hitSize": 21,
	"forceMultiTarget": true,
	"weapons": [
		{
			"name": "marauder-main",
			"reload": 180,
			"x": 22.25,
			"y": 2.75,
			"shootY": 10.5,
			"shootX": 1,
			"parts": [
					{
					"type": "RegionPart",
					"suffix": "-claw",
					"mirror": false	,
					"under": true,
					"progress": "warmup",
					"moveX": 2.75,
					"moveY": 0,
					"x": 0.5,
					"y": 10.25,
				  }

						],
			"top": false,
			"layerOffset": -0.002,
			"mirror": true,
			"alternate": false,
			"continuous": true,
			"rotate": true,
			"rotationLimit": 35,
			"shootSound": "beam",
			"minWarmup": 0.99,
			"shootCone": 40,
			"shootWarmupSpeed": 0.0330,
			"warmupMaintainTime": 150,
			"bullet": {
					"type": "ContinuousLaserBulletType",
					"status": "melting",
					"lifetime": 300,
					"shake": 1,
					"backLength": 4,
					"pierceArmor": true,
					"damage": 30,
					"length": 60,
					"width": 4,
					"drawSize": 500,
					"shootEffect": "shootBigSmoke2",
					"despawnEffect": "smokeCloud",
						}
		},
		{
			"name": "marauder-air",
			"reload": 20,
			"x": 13.25,
			"y": -7.75,
			"shootY": 2.5,
			"shootX": 0,
			"top": true,
			"mirror": true,
			"alternate": true,
			"rotate": true,
			"targetGround": false,
			"shootSound": "shoot",
			"ejectEffect": "casing2",
			"bullet": {
					"type": "BasicBulletType",
					"collidesGround": false,
					"lifetime": 150,
					"pierceArmor": true,
					"homingPower": 0.1,
					"speed": 3,
					"damage": 58,
					"splashDamage": 25,
					"splashDamageRadius": 32,
					"height": 7,
					"width": 5,
					"drawSize": 500,
					"shootEffect": "shootBig",
						}
		},
		{
			"name": "marauder-point",
			"type": "PointDefenseWeapon",
			"reload": 4,
			"x": 0,
			"y": 2.5,
			"shootY": 3.5,
			"shootX": 0,
			"top": true,
			"mirror": false,
			"rotate": true,
			"targetInterval": 4,
			"targetSwitchInterval": 4,
			"recoil": 0.5,
			"bullet": {
					"type": "BulletType",
					"damage": 60,
					"maxRange": 140,
					"shootEffect": "sparkShoot",
					"hitEffect": "pointHit",
						}
		},
	],
	
}